LICENSE
MANIFEST.in
README.md
requirements.txt
setup.py
src/pii_extract/__init__.py
src/pii_extract/defs.py
src/pii_extract/api/__init__.py
src/pii_extract/api/file.py
src/pii_extract/api/processor.py
src/pii_extract/app/__init__.py
src/pii_extract/app/detect.py
src/pii_extract/app/task_info.py
src/pii_extract/build/__init__.py
src/pii_extract/build/build.py
src/pii_extract/build/task/__init__.py
src/pii_extract/build/task/base.py
src/pii_extract/build/task/callable.py
src/pii_extract/build/task/multi.py
src/pii_extract/build/task/regex.py
src/pii_extract/gather/__init__.py
src/pii_extract/gather/collection/__init__.py
src/pii_extract/gather/collection/get.py
src/pii_extract/gather/collection/task_collection.py
src/pii_extract/gather/collection/utils.py
src/pii_extract/gather/collection/sources/__init__.py
src/pii_extract/gather/collection/sources/base.py
src/pii_extract/gather/collection/sources/defs.py
src/pii_extract/gather/collection/sources/folder.py
src/pii_extract/gather/collection/sources/json.py
src/pii_extract/gather/collection/sources/plugin.py
src/pii_extract/gather/collection/sources/utils.py
src/pii_extract/gather/parser/__init__.py
src/pii_extract/gather/parser/defs.py
src/pii_extract/gather/parser/parser.py
src/pii_extract/gather/parser/utils.py
src/pii_extract/helper/__init__.py
src/pii_extract/helper/context.py
src/pii_extract/helper/exception.py
src/pii_extract/helper/json.py
src/pii_extract/helper/logger.py
src/pii_extract/helper/normalizer.py
src/pii_extract/helper/types.py
src/pii_extract/helper/utils.py
src/pii_extract/helper/tasks/__init__.py
src/pii_extract/resources/plugins.json
src/pii_extract_base.egg-info/PKG-INFO
src/pii_extract_base.egg-info/SOURCES.txt
src/pii_extract_base.egg-info/dependency_links.txt
src/pii_extract_base.egg-info/entry_points.txt
src/pii_extract_base.egg-info/requires.txt
src/pii_extract_base.egg-info/top_level.txt